pocketwelt/__init__.py
pocketwelt/colors.py
pocketwelt/configs.py
pocketwelt/encodings.py
pocketwelt/files.py
pocketwelt/imports.py
pocketwelt/logs.py
pocketwelt/modules.py
pocketwelt/objects.py
pocketwelt/paths.py
pocketwelt/processes.py
pocketwelt-0.1.2.dist-info/LICENSE
pocketwelt-0.1.2.dist-info/METADATA
pocketwelt-0.1.2.dist-info/WHEEL
pocketwelt-0.1.2.dist-info/RECORD
